<annotation>
  <folder>train</folder>
  <filename>dog_and_monkey_028</filename>
  <path>dog_and_monkey_028.jpg</path>
  <source>
    <database>Unknown</database>
  </source>
  <size>
    <width>474</width>
    <height>306</height>
    <depth>3</depth>
  </size>
  <segmented>0</segmented>
  <object>
    <name>dog</name>
    <pose>Unspecified</pose>
    <truncated>0</truncated>
    <difficult>0</difficult>
    <bndbox>
      <xmin>34</xmin>
      <ymin>43</ymin>
      <xmax>228</xmax>
      <ymax>282</ymax>
    </bndbox>
  </object>
  <object>
    <name>monkey</name>
    <pose>Unspecified</pose>
    <truncated>0</truncated>
    <difficult>0</difficult>
    <bndbox>
      <xmin>12</xmin>
      <ymin>7</ymin>
      <xmax>474</xmax>
      <ymax>306</ymax>
    </bndbox>
  </object>
</annotation>