<annotation>
  <folder>train</folder>
  <filename>dogs_058</filename>
  <path>dogs_058.jpg</path>
  <source>
    <database>Unknown</database>
  </source>
  <size>
    <width>468</width>
    <height>640</height>
    <depth>3</depth>
  </size>
  <segmented>0</segmented>
  <object>
    <name>dog</name>
    <pose>Unspecified</pose>
    <truncated>0</truncated>
    <difficult>0</difficult>
    <bndbox>
      <xmin>47</xmin>
      <ymin>20</ymin>
      <xmax>393</xmax>
      <ymax>621</ymax>
    </bndbox>
  </object>
</annotation>